tinyworld/__init__.py
tinyworld/audio.py
tinyworld/cli.py
tinyworld/config.py
tinyworld/core.py
tinyworld/effects.py
tinyworld/shapes.py
tinyworld/transitions.py
tinyworld/video.py
tinyworld-0.1.0.dist-info/METADATA
tinyworld-0.1.0.dist-info/WHEEL
tinyworld-0.1.0.dist-info/top_level.txt
tinyworld-0.1.0.dist-info/RECORD
