Metadata-Version: 2.1
Name: tinyworld
Version: 0.1.0
Summary: A small library to create colorful, dynamic videos with TTS audio
Home-page: https://github.com/aaurelions/tinyworld
Author: A. Aurelions
Author-email: "A. Aurelions" <aurelions@protonmail.com>
License: MIT License
Keywords: video,TTS,audio,visualization
Classifier: Development Status :: 3 - Alpha
Classifier: Intended Audience :: Developers
Classifier: License :: OSI Approved :: MIT License
Classifier: Programming Language :: Python :: 3
Classifier: Topic :: Multimedia :: Video
Requires-Python: >=3.7
Requires-Dist: gTTS
Requires-Dist: moviepy
Requires-Dist: Pillow
